wasaclip/__init__.py
wasaclip/main.py
wasaclip-0.2.1.dist-info/METADATA
wasaclip-0.2.1.dist-info/WHEEL
wasaclip-0.2.1.dist-info/entry_points.txt
wasaclip-0.2.1.dist-info/licenses/LICENSE
wasaclip-0.2.1.dist-info/RECORD
