Metadata-Version: 2.4
Name: wasaclip
Version: 0.2.1
Summary: Sharp like wasabi, fast like a ninja — your clipboard’s secret weapon! WasaClip takes your clipboard entries and gives them a spicy refresh! Trim, replace, reformat, or clean up text with lightning speed.
Project-URL: Homepage, https://github.com/rotten77/wasaclip
Project-URL: Bug Tracker, https://github.com/rotten77/wasaclip/issues
Project-URL: Documentation, https://github.com/rotten77/wasaclip
Project-URL: Examples, https://github.com/rotten77/wasaclip/tree/main/examples
Author-email: Jan Zatloukal <zatloukal.jan@gmail.com>
License-File: LICENSE
Classifier: License :: OSI Approved :: Apache Software License
Classifier: Operating System :: OS Independent
Classifier: Programming Language :: Python :: 3
Requires-Python: >=3.11
Requires-Dist: colorama>=0.4.6
Requires-Dist: pyperclip>=1.9.0
